Workbook

Sheet Read Me
A1: Entertainment OS — Operations Workbook (India)
A2: Northwind India Pvt. Ltd. · FY27 Q2 (Jul–Sep 2026) · all amounts in Indian rupees (₹) · generated from the demo run of the agent pipeline
A4: Sheet | B4: What it shows
A5: Policy | B5: Approval thresholds and per-person caps in ₹ (inputs). Change them and every booking's approval chain recalculates.
A6: Bookings | B6: Every booking: request, city, who booked it, who pays, seats/tickets, amount, status and the approval chain the policy requires.
A7: Budgets | B7: Department quarterly budgets vs committed company spend.
A8: Spend by Person | B8: Who is spending how much: company-paid, reimbursable, personal, and share of family/friends group spend.
A9: Expense Reports | B9: Personally-paid spend claimed back, routed to Finance, HR or Benefits.
A10: Group Ledger | B10: Family & friends expenses with each member's share (Splitwise style) and UPI settlements.
A11: Group Balances | B11: Net balance per member = paid − share + settlements sent − settlements received.
A12: Split Calculator | B12: Try a split: enter an amount, pick a method and weights.
A13: Locations | B13: Country → State → City list used by the location picker. 'Other' lets anyone type a place that isn't listed.
A14: Catalog | B14: Films now showing, their languages and formats, and the event types listed near you.
A15: Flow | B15: Step-by-step flow of a request through the agents.
A17: Legend
A18: Blue text | B18: Hard-coded input — safe to edit.
A19: Yellow fill | B19: Key assumption / cell you are expected to change.
A20: Black text | B20: Formula — do not overwrite.

Sheet Policy
A1: Policy inputs (₹)
A2: Source: src/seed.js → POLICY, set by Finance. Edit the blue cells; Bookings column T recalculates.
A4: Threshold | B4: Value (₹) | C4: Meaning
A5: Auto-approve limit | B5: 20000 | C5: Company spend at or below this, within budget and caps, is auto-approved.
A6: Manager limit | B6: 200000 | C6: Above this the department head is added.
A7: Department head limit | B7: 800000 | C7: Above this Finance (CFO) is added.
A10: Per-person caps (company money)
A11: Category key | B11: Cap per person (₹) | C11: Category
A12: movies | B12: 1000 | C12: Movies
A13: events | B13: 25000 | C13: Events & live
A14: reservations | B14: 4000 | C14: Dining
A15: pdr | B15: 5000 | C15: Private dining
A16: catering | B16: 1500 | C16: Catering
A17: gifting | B17: 5000 | C17: Gifting & merch
A18: experiences | B18: 40000 | C18: Experiences
A20: Compliance review categories (client-facing only)
A21: events
A22: gifting

Sheet Bookings
A1: Booking | B1: Date | C1: Category key | D1: Category | E1: Request (as typed) | F1: Title | G1: Vendor / venue | H1: City | I1: State | J1: Booked by | K1: Dept | L1: Who pays | M1: Purpose | N1: Client-facing | O1: Guests / tickets | P1: Amount (₹) | Q1: Per person (₹) | R1: Cap (₹) | S1: Over cap? | T1: Policy approval chain | U1: Approvals recorded by the agents | V1: Status | W1: Group | X1: Seats / tickets
A2: BK-1001 | B2: 2026-09-23 | C2: reservations | D2: Dining | E2: Client dinner for 6 tonight | F2: Client dinner for 6 tonight | G2: Bengaluru Supper Club | H2: Bengaluru | I2: Karnataka | J2: Ananya Iyer | K2: sales | L2: corporate | M2: business | N2: Yes | O2: 6 | P2: 21000 | Q2: =IF(O2>0,P2/O2,0) | R2: =IFERROR(INDEX(Policy!$B$12:$B$18,MATCH(C2,Policy!$A$12:$A$18,0)),0) | S2: =IF(AND(L2="corporate",Q2>R2),"Yes","No") | T2: =IF(L2<>"corporate","None (not company money)",IF(AND(P2<=Policy!$B$5,S2="No"),"Auto-approved","Manager"&IF(OR(P2>Policy!$B$6,S2="Yes")," → Dept head","")&IF(AND(N2="Yes",OR(C2=Policy!$A$21,C2=Policy!$A$22))," → Compliance","")&IF(P2>Policy!$B$7," → Finance",""))) | U2: Manager (Rahul Mehta: pending) | V2: pending_approval
A3: BK-1002 | B3: 2026-10-15 | C3: pdr | D3: Private dining | E3: Private dining room for 30 on 15 Oct for the client summit | F3: Private dining room for 30 on 15 Oct for the client summit | G3: The Mumbai Grand — Private Dining Room | H3: Mumbai | I3: Maharashtra | J3: Rahul Mehta | K3: sales | L3: corporate | M3: business | N3: Yes | O3: 30 | P3: 135000 | Q3: =IF(O3>0,P3/O3,0) | R3: =IFERROR(INDEX(Policy!$B$12:$B$18,MATCH(C3,Policy!$A$12:$A$18,0)),0) | S3: =IF(AND(L3="corporate",Q3>R3),"Yes","No") | T3: =IF(L3<>"corporate","None (not company money)",IF(AND(P3<=Policy!$B$5,S3="No"),"Auto-approved","Manager"&IF(OR(P3>Policy!$B$6,S3="Yes")," → Dept head","")&IF(AND(N3="Yes",OR(C3=Policy!$A$21,C3=Policy!$A$22))," → Compliance","")&IF(P3>Policy!$B$7," → Finance",""))) | U3: Manager (Priya Sharma: approved) | V3: confirmed
A4: BK-1003 | B4: 2026-10-02 | C4: catering | D4: Catering | E4: Offsite lunch catering for 120 people on 2 Oct | F4: Offsite lunch catering for 120 people on 2 Oct | G4: Bengaluru Feast Co. | H4: Bengaluru | I4: Karnataka | J4: Neha Gupta | K4: people | L4: corporate | M4: morale | N4: No | O4: 120 | P4: 168000 | Q4: =IF(O4>0,P4/O4,0) | R4: =IFERROR(INDEX(Policy!$B$12:$B$18,MATCH(C4,Policy!$A$12:$A$18,0)),0) | S4: =IF(AND(L4="corporate",Q4>R4),"Yes","No") | T4: =IF(L4<>"corporate","None (not company money)",IF(AND(P4<=Policy!$B$5,S4="No"),"Auto-approved","Manager"&IF(OR(P4>Policy!$B$6,S4="Yes")," → Dept head","")&IF(AND(N4="Yes",OR(C4=Policy!$A$21,C4=Policy!$A$22))," → Compliance","")&IF(P4>Policy!$B$7," → Finance",""))) | U4: Manager (Vikram Singh: approved) | V4: confirmed
A5: BK-1004 | B5: 2026-11-21 | C5: events | D5: Events & live | E5: Corporate box at the T20 night for 10 clients | F5: T20 Night: Mumbai Chargers vs Capital Kings · 10 × Corporate box (per seat) | G5: Mumbai Cricket Stadium | H5: Mumbai | I5: Maharashtra | J5: Priya Sharma | K5: sales | L5: corporate | M5: business | N5: Yes | O5: 10 | P5: 150000 | Q5: =IF(O5>0,P5/O5,0) | R5: =IFERROR(INDEX(Policy!$B$12:$B$18,MATCH(C5,Policy!$A$12:$A$18,0)),0) | S5: =IF(AND(L5="corporate",Q5>R5),"Yes","No") | T5: =IF(L5<>"corporate","None (not company money)",IF(AND(P5<=Policy!$B$5,S5="No"),"Auto-approved","Manager"&IF(OR(P5>Policy!$B$6,S5="Yes")," → Dept head","")&IF(AND(N5="Yes",OR(C5=Policy!$A$21,C5=Policy!$A$22))," → Compliance","")&IF(P5>Policy!$B$7," → Finance",""))) | U5: Manager (Vikram Singh: approved) → Compliance (Meera Joshi: pending) | V5: pending_approval | X5: 10 × Corporate box (per seat)
A6: BK-1005 | B6: 2026-10-20 | C6: gifting | D6: Gifting & merch | E6: Diwali gift hampers for 60 clients on 20 Oct | F6: Diwali gift hampers for 60 clients on 20 Oct | G6: Bengaluru Artisan Hampers | H6: Bengaluru | I6: Karnataka | J6: Ananya Iyer | K6: sales | L6: corporate | M6: business | N6: Yes | O6: 60 | P6: 210000 | Q6: =IF(O6>0,P6/O6,0) | R6: =IFERROR(INDEX(Policy!$B$12:$B$18,MATCH(C6,Policy!$A$12:$A$18,0)),0) | S6: =IF(AND(L6="corporate",Q6>R6),"Yes","No") | T6: =IF(L6<>"corporate","None (not company money)",IF(AND(P6<=Policy!$B$5,S6="No"),"Auto-approved","Manager"&IF(OR(P6>Policy!$B$6,S6="Yes")," → Dept head","")&IF(AND(N6="Yes",OR(C6=Policy!$A$21,C6=Policy!$A$22))," → Compliance","")&IF(P6>Policy!$B$7," → Finance",""))) | U6: Manager (Rahul Mehta: pending) → Department head (Priya Sharma: pending) → Compliance (Meera Joshi: pending) | V6: pending_approval
A7: BK-1006 | B7: 2026-10-24 | C7: experiences | D7: Experiences | E7: Team offsite retreat for 12 on 24 Oct | F7: Team offsite retreat for 12 on 24 Oct | G7: Coorg coffee-estate retreat | H7: Bengaluru | I7: Karnataka | J7: Kavya Nair | K7: product | L7: corporate | M7: morale | N7: No | O7: 12 | P7: 264000 | Q7: =IF(O7>0,P7/O7,0) | R7: =IFERROR(INDEX(Policy!$B$12:$B$18,MATCH(C7,Policy!$A$12:$A$18,0)),0) | S7: =IF(AND(L7="corporate",Q7>R7),"Yes","No") | T7: =IF(L7<>"corporate","None (not company money)",IF(AND(P7<=Policy!$B$5,S7="No"),"Auto-approved","Manager"&IF(OR(P7>Policy!$B$6,S7="Yes")," → Dept head","")&IF(AND(N7="Yes",OR(C7=Policy!$A$21,C7=Policy!$A$22))," → Compliance","")&IF(P7>Policy!$B$7," → Finance",""))) | U7: Manager (Vikram Singh: approved) | V7: confirmed
A8: BK-1007 | B8: 2026-09-26 | C8: movies | D8: Movies | E8: Team movie night for 8 — Pushpaka Rising IMAX Friday evening | F8: Pushpaka Rising · IMAX · 8 tickets | G8: Starlight Multiplex — Hyderabad Central | H8: Hyderabad | I8: Telangana | J8: Arjun Reddy | K8: product | L8: corporate | M8: morale | N8: No | O8: 8 | P8: 4160 | Q8: =IF(O8>0,P8/O8,0) | R8: =IFERROR(INDEX(Policy!$B$12:$B$18,MATCH(C8,Policy!$A$12:$A$18,0)),0) | S8: =IF(AND(L8="corporate",Q8>R8),"Yes","No") | T8: =IF(L8<>"corporate","None (not company money)",IF(AND(P8<=Policy!$B$5,S8="No"),"Auto-approved","Manager"&IF(OR(P8>Policy!$B$6,S8="Yes")," → Dept head","")&IF(AND(N8="Yes",OR(C8=Policy!$A$21,C8=Policy!$A$22))," → Compliance","")&IF(P8>Policy!$B$7," → Finance",""))) | U8: None | V8: confirmed | X8: IMAX · H4, H5, H6, H7, H8, H9, H10, H11
A9: BK-1008 | B9: 2026-09-26 | C9: movies | D9: Movies | E9: Kaveri Diaries movie with my family Saturday evening | F9: Kaveri Diaries · 2D · 3 tickets | G9: Starlight Multiplex — Bengaluru Central | H9: Bengaluru | I9: Karnataka | J9: Ananya Iyer | K9: sales | L9: shared | M9: personal | N9: No | O9: 3 | P9: 660 | Q9: =IF(O9>0,P9/O9,0) | R9: =IFERROR(INDEX(Policy!$B$12:$B$18,MATCH(C9,Policy!$A$12:$A$18,0)),0) | S9: =IF(AND(L9="corporate",Q9>R9),"Yes","No") | T9: =IF(L9<>"corporate","None (not company money)",IF(AND(P9<=Policy!$B$5,S9="No"),"Auto-approved","Manager"&IF(OR(P9>Policy!$B$6,S9="Yes")," → Dept head","")&IF(AND(N9="Yes",OR(C9=Policy!$A$21,C9=Policy!$A$22))," → Compliance","")&IF(P9>Policy!$B$7," → Finance",""))) | U9: None | V9: confirmed | W9: Iyer family | X9: 2D · G1, G2, G3
A10: BK-1009 | B10: 2026-10-12 | C10: events | D10: Events & live | E10: Stand-up comedy with friends this weekend, split | F10: Stand-up Saturday · 4 × Regular | G10: The Laugh Store, Hyderabad | H10: Hyderabad | I10: Telangana | J10: Arjun Reddy | K10: product | L10: shared | M10: personal | N10: No | O10: 4 | P10: 2000 | Q10: =IF(O10>0,P10/O10,0) | R10: =IFERROR(INDEX(Policy!$B$12:$B$18,MATCH(C10,Policy!$A$12:$A$18,0)),0) | S10: =IF(AND(L10="corporate",Q10>R10),"Yes","No") | T10: =IF(L10<>"corporate","None (not company money)",IF(AND(P10<=Policy!$B$5,S10="No"),"Auto-approved","Manager"&IF(OR(P10>Policy!$B$6,S10="Yes")," → Dept head","")&IF(AND(N10="Yes",OR(C10=Policy!$A$21,C10=Policy!$A$22))," → Compliance","")&IF(P10>Policy!$B$7," → Finance",""))) | U10: None | V10: confirmed | W10: Weekend gang | X10: 4 × Regular
A11: BK-1010 | B11: 2026-09-24 | C11: reservations | D11: Dining | E11: Client lunch for 2 tomorrow, I will pay and expense it | F11: Client lunch for 2 tomorrow, I will pay and expense it | G11: Bengaluru Supper Club | H11: Bengaluru | I11: Karnataka | J11: Ananya Iyer | K11: sales | L11: reimbursable | M11: business | N11: Yes | O11: 2 | P11: 7000 | Q11: =IF(O11>0,P11/O11,0) | R11: =IFERROR(INDEX(Policy!$B$12:$B$18,MATCH(C11,Policy!$A$12:$A$18,0)),0) | S11: =IF(AND(L11="corporate",Q11>R11),"Yes","No") | T11: =IF(L11<>"corporate","None (not company money)",IF(AND(P11<=Policy!$B$5,S11="No"),"Auto-approved","Manager"&IF(OR(P11>Policy!$B$6,S11="Yes")," → Dept head","")&IF(AND(N11="Yes",OR(C11=Policy!$A$21,C11=Policy!$A$22))," → Compliance","")&IF(P11>Policy!$B$7," → Finance",""))) | U11: None | V11: confirmed
A12: BK-1011 | B12: 2026-10-05 | C12: experiences | D12: Experiences | E12: Cooking class on my wellbeing allowance, reimburse me, for 1 on 5 Oct | F12: Cooking class on my wellbeing allowance, reimburse me, for 1 on 5 Oct | G12: Hyderabad Cooking Studio | H12: Hyderabad | I12: Telangana | J12: Arjun Reddy | K12: product | L12: reimbursable | M12: wellbeing | N12: No | O12: 1 | P12: 3000 | Q12: =IF(O12>0,P12/O12,0) | R12: =IFERROR(INDEX(Policy!$B$12:$B$18,MATCH(C12,Policy!$A$12:$A$18,0)),0) | S12: =IF(AND(L12="corporate",Q12>R12),"Yes","No") | T12: =IF(L12<>"corporate","None (not company money)",IF(AND(P12<=Policy!$B$5,S12="No"),"Auto-approved","Manager"&IF(OR(P12>Policy!$B$6,S12="Yes")," → Dept head","")&IF(AND(N12="Yes",OR(C12=Policy!$A$21,C12=Policy!$A$22))," → Compliance","")&IF(P12>Policy!$B$7," → Finance",""))) | U12: None | V12: confirmed
A14: Column T applies the Policy sheet. Column U is what the agents recorded; it also skips self-approval (the requester's own step moves to their manager and duplicates are dropped) and adds Finance when a department budget is exceeded.

Sheet Budgets
A1: Dept key | B1: Department | C1: Cost center | D1: Budget owner | E1: Quarterly budget (₹) | F1: Committed (₹) | G1: Remaining (₹) | H1: Utilisation
A2: sales | B2: Sales | C2: CC-4100 | D2: Priya Sharma | E2: 6000000 | F2: =SUMIFS(Bookings!$P$2:$P$12,Bookings!$K$2:$K$12,A2,Bookings!$L$2:$L$12,"corporate",Bookings!$V$2:$V$12,"pending_approval") + SUMIFS(Bookings!$P$2:$P$12,Bookings!$K$2:$K$12,A2,Bookings!$L$2:$L$12,"corporate",Bookings!$V$2:$V$12,"approved") + SUMIFS(Bookings!$P$2:$P$12,Bookings!$K$2:$K$12,A2,Bookings!$L$2:$L$12,"corporate",Bookings!$V$2:$V$12,"confirmed") | G2: =E2-F2 | H2: =IF(E2>0,F2/E2,0)
A3: product | B3: Product | C3: CC-5200 | D3: Kavya Nair | E3: 2000000 | F3: =SUMIFS(Bookings!$P$2:$P$12,Bookings!$K$2:$K$12,A3,Bookings!$L$2:$L$12,"corporate",Bookings!$V$2:$V$12,"pending_approval") + SUMIFS(Bookings!$P$2:$P$12,Bookings!$K$2:$K$12,A3,Bookings!$L$2:$L$12,"corporate",Bookings!$V$2:$V$12,"approved") + SUMIFS(Bookings!$P$2:$P$12,Bookings!$K$2:$K$12,A3,Bookings!$L$2:$L$12,"corporate",Bookings!$V$2:$V$12,"confirmed") | G3: =E3-F3 | H3: =IF(E3>0,F3/E3,0)
A4: people | B4: People (HR & Benefits) | C4: CC-7100 | D4: Neha Gupta | E4: 3000000 | F4: =SUMIFS(Bookings!$P$2:$P$12,Bookings!$K$2:$K$12,A4,Bookings!$L$2:$L$12,"corporate",Bookings!$V$2:$V$12,"pending_approval") + SUMIFS(Bookings!$P$2:$P$12,Bookings!$K$2:$K$12,A4,Bookings!$L$2:$L$12,"corporate",Bookings!$V$2:$V$12,"approved") + SUMIFS(Bookings!$P$2:$P$12,Bookings!$K$2:$K$12,A4,Bookings!$L$2:$L$12,"corporate",Bookings!$V$2:$V$12,"confirmed") | G4: =E4-F4 | H4: =IF(E4>0,F4/E4,0)
A5: finance | B5: Finance | C5: CC-9000 | D5: Vikram Singh | E5: 1000000 | F5: =SUMIFS(Bookings!$P$2:$P$12,Bookings!$K$2:$K$12,A5,Bookings!$L$2:$L$12,"corporate",Bookings!$V$2:$V$12,"pending_approval") + SUMIFS(Bookings!$P$2:$P$12,Bookings!$K$2:$K$12,A5,Bookings!$L$2:$L$12,"corporate",Bookings!$V$2:$V$12,"approved") + SUMIFS(Bookings!$P$2:$P$12,Bookings!$K$2:$K$12,A5,Bookings!$L$2:$L$12,"corporate",Bookings!$V$2:$V$12,"confirmed") | G5: =E5-F5 | H5: =IF(E5>0,F5/E5,0)
B6: Total | E6: =SUM(E2:E5) | F6: =SUM(F2:F5) | G6: =SUM(G2:G5) | H6: =IF(E6>0,F6/E6,0)
A8: Committed = company-paid bookings awaiting approval, approved or confirmed (Bookings sheet).

Sheet Group Ledger
A1: Expense | B1: Date | C1: Group | D1: Description | E1: Paid by | F1: Amount (₹) | G1: Method | H1: Ananya Iyer | I1: Rohan Iyer | J1: Diya Iyer | K1: Arjun Reddy | L1: Sneha Kapoor | M1: Karthik Rao | N1: Check
A2: EXP-2 | B2: 2026-09-26 | C2: Iyer family | D2: Kaveri Diaries · 2D · 3 tickets | E2: Ananya Iyer | F2: 660 | G2: equal | H2: 220 | I2: 220 | J2: 220 | K2: 0 | L2: 0 | M2: 0 | N2: =IF(ROUND(SUM(H2:M2)-F2,2)=0,"OK","Mismatch")
A3: EXP-3 | B3: 2026-10-12 | C3: Weekend gang | D3: Stand-up Saturday · 4 × Regular | E3: Arjun Reddy | F3: 2000 | G3: equal | H3: 500 | I3: 0 | J3: 0 | K3: 500 | L3: 500 | M3: 500 | N3: =IF(ROUND(SUM(H3:M3)-F3,2)=0,"OK","Mismatch")
A4: EXP-4 | B4: 2026-09-23 | C4: Weekend gang | D4: Cabs to the venue | E4: Sneha Kapoor | F4: 640 | G4: equal | H4: 160 | I4: 0 | J4: 0 | K4: 160 | L4: 160 | M4: 160 | N4: =IF(ROUND(SUM(H4:M4)-F4,2)=0,"OK","Mismatch")
A5: EXP-5 | B5: 2026-09-23 | C5: Iyer family | D5: Groceries for the Onam sadya | E5: Rohan Iyer | F5: 4800 | G5: shares | H5: 1200 | I5: 1200 | J5: 2400 | K5: 0 | L5: 0 | M5: 0 | N5: =IF(ROUND(SUM(H5:M5)-F5,2)=0,"OK","Mismatch")
A7: Shares are computed by the Split agent in whole paise, so each row adds up exactly (Check column).
A9: Settlements (UPI payments recorded)
A10: Settlement | B10: Group | C10: From | D10: To | E10: Amount (₹)
A11: SET-2 | B11: Weekend gang | C11: Karthik Rao | D11: Arjun Reddy | E11: 500

Sheet Group Balances
A1: Group | B1: Member | C1: Paid (₹) | D1: Share (₹) | E1: Settlements sent (₹) | F1: Settlements received (₹) | G1: Net balance (₹) | H1: Position
A2: Iyer family | B2: Ananya Iyer | C2: =SUMIFS('Group Ledger'!$F$2:$F$5,'Group Ledger'!$C$2:$C$5,A2,'Group Ledger'!$E$2:$E$5,B2) | D2: =SUMIFS('Group Ledger'!$H$2:$H$5,'Group Ledger'!$C$2:$C$5,A2) | E2: =SUMIFS('Group Ledger'!$E$11:$E$11,'Group Ledger'!$B$11:$B$11,A2,'Group Ledger'!$C$11:$C$11,B2) | F2: =SUMIFS('Group Ledger'!$E$11:$E$11,'Group Ledger'!$B$11:$B$11,A2,'Group Ledger'!$D$11:$D$11,B2) | G2: =C2-D2+E2-F2 | H2: =IF(ROUND(G2,2)>0,"gets back",IF(ROUND(G2,2)<0,"owes","settled"))
A3: Iyer family | B3: Rohan Iyer | C3: =SUMIFS('Group Ledger'!$F$2:$F$5,'Group Ledger'!$C$2:$C$5,A3,'Group Ledger'!$E$2:$E$5,B3) | D3: =SUMIFS('Group Ledger'!$I$2:$I$5,'Group Ledger'!$C$2:$C$5,A3) | E3: =SUMIFS('Group Ledger'!$E$11:$E$11,'Group Ledger'!$B$11:$B$11,A3,'Group Ledger'!$C$11:$C$11,B3) | F3: =SUMIFS('Group Ledger'!$E$11:$E$11,'Group Ledger'!$B$11:$B$11,A3,'Group Ledger'!$D$11:$D$11,B3) | G3: =C3-D3+E3-F3 | H3: =IF(ROUND(G3,2)>0,"gets back",IF(ROUND(G3,2)<0,"owes","settled"))
A4: Iyer family | B4: Diya Iyer | C4: =SUMIFS('Group Ledger'!$F$2:$F$5,'Group Ledger'!$C$2:$C$5,A4,'Group Ledger'!$E$2:$E$5,B4) | D4: =SUMIFS('Group Ledger'!$J$2:$J$5,'Group Ledger'!$C$2:$C$5,A4) | E4: =SUMIFS('Group Ledger'!$E$11:$E$11,'Group Ledger'!$B$11:$B$11,A4,'Group Ledger'!$C$11:$C$11,B4) | F4: =SUMIFS('Group Ledger'!$E$11:$E$11,'Group Ledger'!$B$11:$B$11,A4,'Group Ledger'!$D$11:$D$11,B4) | G4: =C4-D4+E4-F4 | H4: =IF(ROUND(G4,2)>0,"gets back",IF(ROUND(G4,2)<0,"owes","settled"))
A5: Weekend gang | B5: Ananya Iyer | C5: =SUMIFS('Group Ledger'!$F$2:$F$5,'Group Ledger'!$C$2:$C$5,A5,'Group Ledger'!$E$2:$E$5,B5) | D5: =SUMIFS('Group Ledger'!$H$2:$H$5,'Group Ledger'!$C$2:$C$5,A5) | E5: =SUMIFS('Group Ledger'!$E$11:$E$11,'Group Ledger'!$B$11:$B$11,A5,'Group Ledger'!$C$11:$C$11,B5) | F5: =SUMIFS('Group Ledger'!$E$11:$E$11,'Group Ledger'!$B$11:$B$11,A5,'Group Ledger'!$D$11:$D$11,B5) | G5: =C5-D5+E5-F5 | H5: =IF(ROUND(G5,2)>0,"gets back",IF(ROUND(G5,2)<0,"owes","settled"))
A6: Weekend gang | B6: Arjun Reddy | C6: =SUMIFS('Group Ledger'!$F$2:$F$5,'Group Ledger'!$C$2:$C$5,A6,'Group Ledger'!$E$2:$E$5,B6) | D6: =SUMIFS('Group Ledger'!$K$2:$K$5,'Group Ledger'!$C$2:$C$5,A6) | E6: =SUMIFS('Group Ledger'!$E$11:$E$11,'Group Ledger'!$B$11:$B$11,A6,'Group Ledger'!$C$11:$C$11,B6) | F6: =SUMIFS('Group Ledger'!$E$11:$E$11,'Group Ledger'!$B$11:$B$11,A6,'Group Ledger'!$D$11:$D$11,B6) | G6: =C6-D6+E6-F6 | H6: =IF(ROUND(G6,2)>0,"gets back",IF(ROUND(G6,2)<0,"owes","settled"))
A7: Weekend gang | B7: Sneha Kapoor | C7: =SUMIFS('Group Ledger'!$F$2:$F$5,'Group Ledger'!$C$2:$C$5,A7,'Group Ledger'!$E$2:$E$5,B7) | D7: =SUMIFS('Group Ledger'!$L$2:$L$5,'Group Ledger'!$C$2:$C$5,A7) | E7: =SUMIFS('Group Ledger'!$E$11:$E$11,'Group Ledger'!$B$11:$B$11,A7,'Group Ledger'!$C$11:$C$11,B7) | F7: =SUMIFS('Group Ledger'!$E$11:$E$11,'Group Ledger'!$B$11:$B$11,A7,'Group Ledger'!$D$11:$D$11,B7) | G7: =C7-D7+E7-F7 | H7: =IF(ROUND(G7,2)>0,"gets back",IF(ROUND(G7,2)<0,"owes","settled"))
A8: Weekend gang | B8: Karthik Rao | C8: =SUMIFS('Group Ledger'!$F$2:$F$5,'Group Ledger'!$C$2:$C$5,A8,'Group Ledger'!$E$2:$E$5,B8) | D8: =SUMIFS('Group Ledger'!$M$2:$M$5,'Group Ledger'!$C$2:$C$5,A8) | E8: =SUMIFS('Group Ledger'!$E$11:$E$11,'Group Ledger'!$B$11:$B$11,A8,'Group Ledger'!$C$11:$C$11,B8) | F8: =SUMIFS('Group Ledger'!$E$11:$E$11,'Group Ledger'!$B$11:$B$11,A8,'Group Ledger'!$D$11:$D$11,B8) | G8: =C8-D8+E8-F8 | H8: =IF(ROUND(G8,2)>0,"gets back",IF(ROUND(G8,2)<0,"owes","settled"))
A10: Positive: is owed money. Negative: owes money. Each group sums to zero.

Sheet Spend by Person
A1: Person | B1: Title | C1: Employee | D1: Company-paid (₹) | E1: Reimbursable (₹) | F1: Personal (₹) | G1: Paid for groups (₹) | H1: Own group share (₹) | I1: Out of pocket (₹) | J1: Total handled (₹)
A2: Ananya Iyer | B2: Account Executive | C2: Yes | D2: =SUMIFS(Bookings!$P$2:$P$12,Bookings!$J$2:$J$12,$A2,Bookings!$L$2:$L$12,"corporate",Bookings!$V$2:$V$12,"pending_approval") + SUMIFS(Bookings!$P$2:$P$12,Bookings!$J$2:$J$12,$A2,Bookings!$L$2:$L$12,"corporate",Bookings!$V$2:$V$12,"approved") + SUMIFS(Bookings!$P$2:$P$12,Bookings!$J$2:$J$12,$A2,Bookings!$L$2:$L$12,"corporate",Bookings!$V$2:$V$12,"confirmed") | E2: =SUMIFS(Bookings!$P$2:$P$12,Bookings!$J$2:$J$12,$A2,Bookings!$L$2:$L$12,"reimbursable",Bookings!$V$2:$V$12,"pending_approval") + SUMIFS(Bookings!$P$2:$P$12,Bookings!$J$2:$J$12,$A2,Bookings!$L$2:$L$12,"reimbursable",Bookings!$V$2:$V$12,"approved") + SUMIFS(Bookings!$P$2:$P$12,Bookings!$J$2:$J$12,$A2,Bookings!$L$2:$L$12,"reimbursable",Bookings!$V$2:$V$12,"confirmed") | F2: =SUMIFS(Bookings!$P$2:$P$12,Bookings!$J$2:$J$12,$A2,Bookings!$L$2:$L$12,"personal",Bookings!$V$2:$V$12,"pending_approval") + SUMIFS(Bookings!$P$2:$P$12,Bookings!$J$2:$J$12,$A2,Bookings!$L$2:$L$12,"personal",Bookings!$V$2:$V$12,"approved") + SUMIFS(Bookings!$P$2:$P$12,Bookings!$J$2:$J$12,$A2,Bookings!$L$2:$L$12,"personal",Bookings!$V$2:$V$12,"confirmed") | G2: =SUMIFS('Group Ledger'!$F$2:$F$5,'Group Ledger'!$E$2:$E$5,A2) | H2: =SUM('Group Ledger'!H2:H5) | I2: =E2+F2+H2 | J2: =D2+E2+F2+G2
A3: Rahul Mehta | B3: Sales Director | C3: Yes | D3: =SUMIFS(Bookings!$P$2:$P$12,Bookings!$J$2:$J$12,$A3,Bookings!$L$2:$L$12,"corporate",Bookings!$V$2:$V$12,"pending_approval") + SUMIFS(Bookings!$P$2:$P$12,Bookings!$J$2:$J$12,$A3,Bookings!$L$2:$L$12,"corporate",Bookings!$V$2:$V$12,"approved") + SUMIFS(Bookings!$P$2:$P$12,Bookings!$J$2:$J$12,$A3,Bookings!$L$2:$L$12,"corporate",Bookings!$V$2:$V$12,"confirmed") | E3: =SUMIFS(Bookings!$P$2:$P$12,Bookings!$J$2:$J$12,$A3,Bookings!$L$2:$L$12,"reimbursable",Bookings!$V$2:$V$12,"pending_approval") + SUMIFS(Bookings!$P$2:$P$12,Bookings!$J$2:$J$12,$A3,Bookings!$L$2:$L$12,"reimbursable",Bookings!$V$2:$V$12,"approved") + SUMIFS(Bookings!$P$2:$P$12,Bookings!$J$2:$J$12,$A3,Bookings!$L$2:$L$12,"reimbursable",Bookings!$V$2:$V$12,"confirmed") | F3: =SUMIFS(Bookings!$P$2:$P$12,Bookings!$J$2:$J$12,$A3,Bookings!$L$2:$L$12,"personal",Bookings!$V$2:$V$12,"pending_approval") + SUMIFS(Bookings!$P$2:$P$12,Bookings!$J$2:$J$12,$A3,Bookings!$L$2:$L$12,"personal",Bookings!$V$2:$V$12,"approved") + SUMIFS(Bookings!$P$2:$P$12,Bookings!$J$2:$J$12,$A3,Bookings!$L$2:$L$12,"personal",Bookings!$V$2:$V$12,"confirmed") | G3: =SUMIFS('Group Ledger'!$F$2:$F$5,'Group Ledger'!$E$2:$E$5,A3) | H3: 0 | I3: =E3+F3+H3 | J3: =D3+E3+F3+G3
A4: Priya Sharma | B4: VP Sales (Dept Head) | C4: Yes | D4: =SUMIFS(Bookings!$P$2:$P$12,Bookings!$J$2:$J$12,$A4,Bookings!$L$2:$L$12,"corporate",Bookings!$V$2:$V$12,"pending_approval") + SUMIFS(Bookings!$P$2:$P$12,Bookings!$J$2:$J$12,$A4,Bookings!$L$2:$L$12,"corporate",Bookings!$V$2:$V$12,"approved") + SUMIFS(Bookings!$P$2:$P$12,Bookings!$J$2:$J$12,$A4,Bookings!$L$2:$L$12,"corporate",Bookings!$V$2:$V$12,"confirmed") | E4: =SUMIFS(Bookings!$P$2:$P$12,Bookings!$J$2:$J$12,$A4,Bookings!$L$2:$L$12,"reimbursable",Bookings!$V$2:$V$12,"pending_approval") + SUMIFS(Bookings!$P$2:$P$12,Bookings!$J$2:$J$12,$A4,Bookings!$L$2:$L$12,"reimbursable",Bookings!$V$2:$V$12,"approved") + SUMIFS(Bookings!$P$2:$P$12,Bookings!$J$2:$J$12,$A4,Bookings!$L$2:$L$12,"reimbursable",Bookings!$V$2:$V$12,"confirmed") | F4: =SUMIFS(Bookings!$P$2:$P$12,Bookings!$J$2:$J$12,$A4,Bookings!$L$2:$L$12,"personal",Bookings!$V$2:$V$12,"pending_approval") + SUMIFS(Bookings!$P$2:$P$12,Bookings!$J$2:$J$12,$A4,Bookings!$L$2:$L$12,"personal",Bookings!$V$2:$V$12,"approved") + SUMIFS(Bookings!$P$2:$P$12,Bookings!$J$2:$J$12,$A4,Bookings!$L$2:$L$12,"personal",Bookings!$V$2:$V$12,"confirmed") | G4: =SUMIFS('Group Ledger'!$F$2:$F$5,'Group Ledger'!$E$2:$E$5,A4) | H4: 0 | I4: =E4+F4+H4 | J4: =D4+E4+F4+G4
A5: Arjun Reddy | B5: Product Manager | C5: Yes | D5: =SUMIFS(Bookings!$P$2:$P$12,Bookings!$J$2:$J$12,$A5,Bookings!$L$2:$L$12,"corporate",Bookings!$V$2:$V$12,"pending_approval") + SUMIFS(Bookings!$P$2:$P$12,Bookings!$J$2:$J$12,$A5,Bookings!$L$2:$L$12,"corporate",Bookings!$V$2:$V$12,"approved") + SUMIFS(Bookings!$P$2:$P$12,Bookings!$J$2:$J$12,$A5,Bookings!$L$2:$L$12,"corporate",Bookings!$V$2:$V$12,"confirmed") | E5: =SUMIFS(Bookings!$P$2:$P$12,Bookings!$J$2:$J$12,$A5,Bookings!$L$2:$L$12,"reimbursable",Bookings!$V$2:$V$12,"pending_approval") + SUMIFS(Bookings!$P$2:$P$12,Bookings!$J$2:$J$12,$A5,Bookings!$L$2:$L$12,"reimbursable",Bookings!$V$2:$V$12,"approved") + SUMIFS(Bookings!$P$2:$P$12,Bookings!$J$2:$J$12,$A5,Bookings!$L$2:$L$12,"reimbursable",Bookings!$V$2:$V$12,"confirmed") | F5: =SUMIFS(Bookings!$P$2:$P$12,Bookings!$J$2:$J$12,$A5,Bookings!$L$2:$L$12,"personal",Bookings!$V$2:$V$12,"pending_approval") + SUMIFS(Bookings!$P$2:$P$12,Bookings!$J$2:$J$12,$A5,Bookings!$L$2:$L$12,"personal",Bookings!$V$2:$V$12,"approved") + SUMIFS(Bookings!$P$2:$P$12,Bookings!$J$2:$J$12,$A5,Bookings!$L$2:$L$12,"personal",Bookings!$V$2:$V$12,"confirmed") | G5: =SUMIFS('Group Ledger'!$F$2:$F$5,'Group Ledger'!$E$2:$E$5,A5) | H5: =SUM('Group Ledger'!K2:K5) | I5: =E5+F5+H5 | J5: =D5+E5+F5+G5
A6: Kavya Nair | B6: Head of Product (Dept Head) | C6: Yes | D6: =SUMIFS(Bookings!$P$2:$P$12,Bookings!$J$2:$J$12,$A6,Bookings!$L$2:$L$12,"corporate",Bookings!$V$2:$V$12,"pending_approval") + SUMIFS(Bookings!$P$2:$P$12,Bookings!$J$2:$J$12,$A6,Bookings!$L$2:$L$12,"corporate",Bookings!$V$2:$V$12,"approved") + SUMIFS(Bookings!$P$2:$P$12,Bookings!$J$2:$J$12,$A6,Bookings!$L$2:$L$12,"corporate",Bookings!$V$2:$V$12,"confirmed") | E6: =SUMIFS(Bookings!$P$2:$P$12,Bookings!$J$2:$J$12,$A6,Bookings!$L$2:$L$12,"reimbursable",Bookings!$V$2:$V$12,"pending_approval") + SUMIFS(Bookings!$P$2:$P$12,Bookings!$J$2:$J$12,$A6,Bookings!$L$2:$L$12,"reimbursable",Bookings!$V$2:$V$12,"approved") + SUMIFS(Bookings!$P$2:$P$12,Bookings!$J$2:$J$12,$A6,Bookings!$L$2:$L$12,"reimbursable",Bookings!$V$2:$V$12,"confirmed") | F6: =SUMIFS(Bookings!$P$2:$P$12,Bookings!$J$2:$J$12,$A6,Bookings!$L$2:$L$12,"personal",Bookings!$V$2:$V$12,"pending_approval") + SUMIFS(Bookings!$P$2:$P$12,Bookings!$J$2:$J$12,$A6,Bookings!$L$2:$L$12,"personal",Bookings!$V$2:$V$12,"approved") + SUMIFS(Bookings!$P$2:$P$12,Bookings!$J$2:$J$12,$A6,Bookings!$L$2:$L$12,"personal",Bookings!$V$2:$V$12,"confirmed") | G6: =SUMIFS('Group Ledger'!$F$2:$F$5,'Group Ledger'!$E$2:$E$5,A6) | H6: 0 | I6: =E6+F6+H6 | J6: =D6+E6+F6+G6
A7: Vikram Singh | B7: CFO (Finance) | C7: Yes | D7: =SUMIFS(Bookings!$P$2:$P$12,Bookings!$J$2:$J$12,$A7,Bookings!$L$2:$L$12,"corporate",Bookings!$V$2:$V$12,"pending_approval") + SUMIFS(Bookings!$P$2:$P$12,Bookings!$J$2:$J$12,$A7,Bookings!$L$2:$L$12,"corporate",Bookings!$V$2:$V$12,"approved") + SUMIFS(Bookings!$P$2:$P$12,Bookings!$J$2:$J$12,$A7,Bookings!$L$2:$L$12,"corporate",Bookings!$V$2:$V$12,"confirmed") | E7: =SUMIFS(Bookings!$P$2:$P$12,Bookings!$J$2:$J$12,$A7,Bookings!$L$2:$L$12,"reimbursable",Bookings!$V$2:$V$12,"pending_approval") + SUMIFS(Bookings!$P$2:$P$12,Bookings!$J$2:$J$12,$A7,Bookings!$L$2:$L$12,"reimbursable",Bookings!$V$2:$V$12,"approved") + SUMIFS(Bookings!$P$2:$P$12,Bookings!$J$2:$J$12,$A7,Bookings!$L$2:$L$12,"reimbursable",Bookings!$V$2:$V$12,"confirmed") | F7: =SUMIFS(Bookings!$P$2:$P$12,Bookings!$J$2:$J$12,$A7,Bookings!$L$2:$L$12,"personal",Bookings!$V$2:$V$12,"pending_approval") + SUMIFS(Bookings!$P$2:$P$12,Bookings!$J$2:$J$12,$A7,Bookings!$L$2:$L$12,"personal",Bookings!$V$2:$V$12,"approved") + SUMIFS(Bookings!$P$2:$P$12,Bookings!$J$2:$J$12,$A7,Bookings!$L$2:$L$12,"personal",Bookings!$V$2:$V$12,"confirmed") | G7: =SUMIFS('Group Ledger'!$F$2:$F$5,'Group Ledger'!$E$2:$E$5,A7) | H7: 0 | I7: =E7+F7+H7 | J7: =D7+E7+F7+G7
A8: Neha Gupta | B8: HR Business Partner | C8: Yes | D8: =SUMIFS(Bookings!$P$2:$P$12,Bookings!$J$2:$J$12,$A8,Bookings!$L$2:$L$12,"corporate",Bookings!$V$2:$V$12,"pending_approval") + SUMIFS(Bookings!$P$2:$P$12,Bookings!$J$2:$J$12,$A8,Bookings!$L$2:$L$12,"corporate",Bookings!$V$2:$V$12,"approved") + SUMIFS(Bookings!$P$2:$P$12,Bookings!$J$2:$J$12,$A8,Bookings!$L$2:$L$12,"corporate",Bookings!$V$2:$V$12,"confirmed") | E8: =SUMIFS(Bookings!$P$2:$P$12,Bookings!$J$2:$J$12,$A8,Bookings!$L$2:$L$12,"reimbursable",Bookings!$V$2:$V$12,"pending_approval") + SUMIFS(Bookings!$P$2:$P$12,Bookings!$J$2:$J$12,$A8,Bookings!$L$2:$L$12,"reimbursable",Bookings!$V$2:$V$12,"approved") + SUMIFS(Bookings!$P$2:$P$12,Bookings!$J$2:$J$12,$A8,Bookings!$L$2:$L$12,"reimbursable",Bookings!$V$2:$V$12,"confirmed") | F8: =SUMIFS(Bookings!$P$2:$P$12,Bookings!$J$2:$J$12,$A8,Bookings!$L$2:$L$12,"personal",Bookings!$V$2:$V$12,"pending_approval") + SUMIFS(Bookings!$P$2:$P$12,Bookings!$J$2:$J$12,$A8,Bookings!$L$2:$L$12,"personal",Bookings!$V$2:$V$12,"approved") + SUMIFS(Bookings!$P$2:$P$12,Bookings!$J$2:$J$12,$A8,Bookings!$L$2:$L$12,"personal",Bookings!$V$2:$V$12,"confirmed") | G8: =SUMIFS('Group Ledger'!$F$2:$F$5,'Group Ledger'!$E$2:$E$5,A8) | H8: 0 | I8: =E8+F8+H8 | J8: =D8+E8+F8+G8
A9: Farhan Qureshi | B9: Benefits Lead | C9: Yes | D9: =SUMIFS(Bookings!$P$2:$P$12,Bookings!$J$2:$J$12,$A9,Bookings!$L$2:$L$12,"corporate",Bookings!$V$2:$V$12,"pending_approval") + SUMIFS(Bookings!$P$2:$P$12,Bookings!$J$2:$J$12,$A9,Bookings!$L$2:$L$12,"corporate",Bookings!$V$2:$V$12,"approved") + SUMIFS(Bookings!$P$2:$P$12,Bookings!$J$2:$J$12,$A9,Bookings!$L$2:$L$12,"corporate",Bookings!$V$2:$V$12,"confirmed") | E9: =SUMIFS(Bookings!$P$2:$P$12,Bookings!$J$2:$J$12,$A9,Bookings!$L$2:$L$12,"reimbursable",Bookings!$V$2:$V$12,"pending_approval") + SUMIFS(Bookings!$P$2:$P$12,Bookings!$J$2:$J$12,$A9,Bookings!$L$2:$L$12,"reimbursable",Bookings!$V$2:$V$12,"approved") + SUMIFS(Bookings!$P$2:$P$12,Bookings!$J$2:$J$12,$A9,Bookings!$L$2:$L$12,"reimbursable",Bookings!$V$2:$V$12,"confirmed") | F9: =SUMIFS(Bookings!$P$2:$P$12,Bookings!$J$2:$J$12,$A9,Bookings!$L$2:$L$12,"personal",Bookings!$V$2:$V$12,"pending_approval") + SUMIFS(Bookings!$P$2:$P$12,Bookings!$J$2:$J$12,$A9,Bookings!$L$2:$L$12,"personal",Bookings!$V$2:$V$12,"approved") + SUMIFS(Bookings!$P$2:$P$12,Bookings!$J$2:$J$12,$A9,Bookings!$L$2:$L$12,"personal",Bookings!$V$2:$V$12,"confirmed") | G9: =SUMIFS('Group Ledger'!$F$2:$F$5,'Group Ledger'!$E$2:$E$5,A9) | H9: 0 | I9: =E9+F9+H9 | J9: =D9+E9+F9+G9
A10: Meera Joshi | B10: Compliance Officer | C10: Yes | D10: =SUMIFS(Bookings!$P$2:$P$12,Bookings!$J$2:$J$12,$A10,Bookings!$L$2:$L$12,"corporate",Bookings!$V$2:$V$12,"pending_approval") + SUMIFS(Bookings!$P$2:$P$12,Bookings!$J$2:$J$12,$A10,Bookings!$L$2:$L$12,"corporate",Bookings!$V$2:$V$12,"approved") + SUMIFS(Bookings!$P$2:$P$12,Bookings!$J$2:$J$12,$A10,Bookings!$L$2:$L$12,"corporate",Bookings!$V$2:$V$12,"confirmed") | E10: =SUMIFS(Bookings!$P$2:$P$12,Bookings!$J$2:$J$12,$A10,Bookings!$L$2:$L$12,"reimbursable",Bookings!$V$2:$V$12,"pending_approval") + SUMIFS(Bookings!$P$2:$P$12,Bookings!$J$2:$J$12,$A10,Bookings!$L$2:$L$12,"reimbursable",Bookings!$V$2:$V$12,"approved") + SUMIFS(Bookings!$P$2:$P$12,Bookings!$J$2:$J$12,$A10,Bookings!$L$2:$L$12,"reimbursable",Bookings!$V$2:$V$12,"confirmed") | F10: =SUMIFS(Bookings!$P$2:$P$12,Bookings!$J$2:$J$12,$A10,Bookings!$L$2:$L$12,"personal",Bookings!$V$2:$V$12,"pending_approval") + SUMIFS(Bookings!$P$2:$P$12,Bookings!$J$2:$J$12,$A10,Bookings!$L$2:$L$12,"personal",Bookings!$V$2:$V$12,"approved") + SUMIFS(Bookings!$P$2:$P$12,Bookings!$J$2:$J$12,$A10,Bookings!$L$2:$L$12,"personal",Bookings!$V$2:$V$12,"confirmed") | G10: =SUMIFS('Group Ledger'!$F$2:$F$5,'Group Ledger'!$E$2:$E$5,A10) | H10: 0 | I10: =E10+F10+H10 | J10: =D10+E10+F10+G10
A11: Rohan Iyer | B11: Family (Ananya’s husband) | C11: Guest | D11: =SUMIFS(Bookings!$P$2:$P$12,Bookings!$J$2:$J$12,$A11,Bookings!$L$2:$L$12,"corporate",Bookings!$V$2:$V$12,"pending_approval") + SUMIFS(Bookings!$P$2:$P$12,Bookings!$J$2:$J$12,$A11,Bookings!$L$2:$L$12,"corporate",Bookings!$V$2:$V$12,"approved") + SUMIFS(Bookings!$P$2:$P$12,Bookings!$J$2:$J$12,$A11,Bookings!$L$2:$L$12,"corporate",Bookings!$V$2:$V$12,"confirmed") | E11: =SUMIFS(Bookings!$P$2:$P$12,Bookings!$J$2:$J$12,$A11,Bookings!$L$2:$L$12,"reimbursable",Bookings!$V$2:$V$12,"pending_approval") + SUMIFS(Bookings!$P$2:$P$12,Bookings!$J$2:$J$12,$A11,Bookings!$L$2:$L$12,"reimbursable",Bookings!$V$2:$V$12,"approved") + SUMIFS(Bookings!$P$2:$P$12,Bookings!$J$2:$J$12,$A11,Bookings!$L$2:$L$12,"reimbursable",Bookings!$V$2:$V$12,"confirmed") | F11: =SUMIFS(Bookings!$P$2:$P$12,Bookings!$J$2:$J$12,$A11,Bookings!$L$2:$L$12,"personal",Bookings!$V$2:$V$12,"pending_approval") + SUMIFS(Bookings!$P$2:$P$12,Bookings!$J$2:$J$12,$A11,Bookings!$L$2:$L$12,"personal",Bookings!$V$2:$V$12,"approved") + SUMIFS(Bookings!$P$2:$P$12,Bookings!$J$2:$J$12,$A11,Bookings!$L$2:$L$12,"personal",Bookings!$V$2:$V$12,"confirmed") | G11: =SUMIFS('Group Ledger'!$F$2:$F$5,'Group Ledger'!$E$2:$E$5,A11) | H11: =SUM('Group Ledger'!I2:I5) | I11: =E11+F11+H11 | J11: =D11+E11+F11+G11
A12: Diya Iyer | B12: Family (Ananya’s sister) | C12: Guest | D12: =SUMIFS(Bookings!$P$2:$P$12,Bookings!$J$2:$J$12,$A12,Bookings!$L$2:$L$12,"corporate",Bookings!$V$2:$V$12,"pending_approval") + SUMIFS(Bookings!$P$2:$P$12,Bookings!$J$2:$J$12,$A12,Bookings!$L$2:$L$12,"corporate",Bookings!$V$2:$V$12,"approved") + SUMIFS(Bookings!$P$2:$P$12,Bookings!$J$2:$J$12,$A12,Bookings!$L$2:$L$12,"corporate",Bookings!$V$2:$V$12,"confirmed") | E12: =SUMIFS(Bookings!$P$2:$P$12,Bookings!$J$2:$J$12,$A12,Bookings!$L$2:$L$12,"reimbursable",Bookings!$V$2:$V$12,"pending_approval") + SUMIFS(Bookings!$P$2:$P$12,Bookings!$J$2:$J$12,$A12,Bookings!$L$2:$L$12,"reimbursable",Bookings!$V$2:$V$12,"approved") + SUMIFS(Bookings!$P$2:$P$12,Bookings!$J$2:$J$12,$A12,Bookings!$L$2:$L$12,"reimbursable",Bookings!$V$2:$V$12,"confirmed") | F12: =SUMIFS(Bookings!$P$2:$P$12,Bookings!$J$2:$J$12,$A12,Bookings!$L$2:$L$12,"personal",Bookings!$V$2:$V$12,"pending_approval") + SUMIFS(Bookings!$P$2:$P$12,Bookings!$J$2:$J$12,$A12,Bookings!$L$2:$L$12,"personal",Bookings!$V$2:$V$12,"approved") + SUMIFS(Bookings!$P$2:$P$12,Bookings!$J$2:$J$12,$A12,Bookings!$L$2:$L$12,"personal",Bookings!$V$2:$V$12,"confirmed") | G12: =SUMIFS('Group Ledger'!$F$2:$F$5,'Group Ledger'!$E$2:$E$5,A12) | H12: =SUM('Group Ledger'!J2:J5) | I12: =E12+F12+H12 | J12: =D12+E12+F12+G12
A13: Sneha Kapoor | B13: Friend | C13: Guest | D13: =SUMIFS(Bookings!$P$2:$P$12,Bookings!$J$2:$J$12,$A13,Bookings!$L$2:$L$12,"corporate",Bookings!$V$2:$V$12,"pending_approval") + SUMIFS(Bookings!$P$2:$P$12,Bookings!$J$2:$J$12,$A13,Bookings!$L$2:$L$12,"corporate",Bookings!$V$2:$V$12,"approved") + SUMIFS(Bookings!$P$2:$P$12,Bookings!$J$2:$J$12,$A13,Bookings!$L$2:$L$12,"corporate",Bookings!$V$2:$V$12,"confirmed") | E13: =SUMIFS(Bookings!$P$2:$P$12,Bookings!$J$2:$J$12,$A13,Bookings!$L$2:$L$12,"reimbursable",Bookings!$V$2:$V$12,"pending_approval") + SUMIFS(Bookings!$P$2:$P$12,Bookings!$J$2:$J$12,$A13,Bookings!$L$2:$L$12,"reimbursable",Bookings!$V$2:$V$12,"approved") + SUMIFS(Bookings!$P$2:$P$12,Bookings!$J$2:$J$12,$A13,Bookings!$L$2:$L$12,"reimbursable",Bookings!$V$2:$V$12,"confirmed") | F13: =SUMIFS(Bookings!$P$2:$P$12,Bookings!$J$2:$J$12,$A13,Bookings!$L$2:$L$12,"personal",Bookings!$V$2:$V$12,"pending_approval") + SUMIFS(Bookings!$P$2:$P$12,Bookings!$J$2:$J$12,$A13,Bookings!$L$2:$L$12,"personal",Bookings!$V$2:$V$12,"approved") + SUMIFS(Bookings!$P$2:$P$12,Bookings!$J$2:$J$12,$A13,Bookings!$L$2:$L$12,"personal",Bookings!$V$2:$V$12,"confirmed") | G13: =SUMIFS('Group Ledger'!$F$2:$F$5,'Group Ledger'!$E$2:$E$5,A13) | H13: =SUM('Group Ledger'!L2:L5) | I13: =E13+F13+H13 | J13: =D13+E13+F13+G13
A14: Karthik Rao | B14: Friend | C14: Guest | D14: =SUMIFS(Bookings!$P$2:$P$12,Bookings!$J$2:$J$12,$A14,Bookings!$L$2:$L$12,"corporate",Bookings!$V$2:$V$12,"pending_approval") + SUMIFS(Bookings!$P$2:$P$12,Bookings!$J$2:$J$12,$A14,Bookings!$L$2:$L$12,"corporate",Bookings!$V$2:$V$12,"approved") + SUMIFS(Bookings!$P$2:$P$12,Bookings!$J$2:$J$12,$A14,Bookings!$L$2:$L$12,"corporate",Bookings!$V$2:$V$12,"confirmed") | E14: =SUMIFS(Bookings!$P$2:$P$12,Bookings!$J$2:$J$12,$A14,Bookings!$L$2:$L$12,"reimbursable",Bookings!$V$2:$V$12,"pending_approval") + SUMIFS(Bookings!$P$2:$P$12,Bookings!$J$2:$J$12,$A14,Bookings!$L$2:$L$12,"reimbursable",Bookings!$V$2:$V$12,"approved") + SUMIFS(Bookings!$P$2:$P$12,Bookings!$J$2:$J$12,$A14,Bookings!$L$2:$L$12,"reimbursable",Bookings!$V$2:$V$12,"confirmed") | F14: =SUMIFS(Bookings!$P$2:$P$12,Bookings!$J$2:$J$12,$A14,Bookings!$L$2:$L$12,"personal",Bookings!$V$2:$V$12,"pending_approval") + SUMIFS(Bookings!$P$2:$P$12,Bookings!$J$2:$J$12,$A14,Bookings!$L$2:$L$12,"personal",Bookings!$V$2:$V$12,"approved") + SUMIFS(Bookings!$P$2:$P$12,Bookings!$J$2:$J$12,$A14,Bookings!$L$2:$L$12,"personal",Bookings!$V$2:$V$12,"confirmed") | G14: =SUMIFS('Group Ledger'!$F$2:$F$5,'Group Ledger'!$E$2:$E$5,A14) | H14: =SUM('Group Ledger'!M2:M5) | I14: =E14+F14+H14 | J14: =D14+E14+F14+G14
A15: Total | D15: =SUM(D2:D14) | E15: =SUM(E2:E14) | F15: =SUM(F2:F14) | G15: =SUM(G2:G14) | H15: =SUM(H2:H14) | I15: =SUM(I2:I14) | J15: =SUM(J2:J14)
A17: Only live bookings count (awaiting approval, approved, confirmed). Out of pocket = reimbursable + personal + own share of group spend.

Sheet Expense Reports
A1: Report | B1: Owner | C1: Type | D1: Routed to | E1: Lines | F1: Bookings | G1: Total (₹) | H1: Claimable (₹) | I1: Approval chain | J1: Status | K1: Submitted
A2: ER-502 | B2: Arjun Reddy | C2: Lifestyle & wellbeing allowance | D2: Benefits | E2: 1 | F2: BK-1011 | G2: 3000 | H2: 3000 | I2: Benefits team (Farhan Qureshi: approved) | J2: reimbursed | K2: 2026-09-23T00:00:35.488Z
A3: ER-501 | B3: Ananya Iyer | C3: Business / client entertainment | D3: Finance | E3: 1 | F3: BK-1010 | G3: 7000 | H3: 7000 | I3: Manager (Rahul Mehta: approved) → Finance team (Vikram Singh: pending) | J3: submitted | K3: 2026-09-23T00:00:35.488Z
A5: Routing rules
A6: Client / business | C6: Manager → Finance
A7: Team morale, celebrations & offsites | C7: Manager → HR
A8: Lifestyle & wellbeing allowance | C8: Benefits (capped at the allowance balance)

Sheet Split Calculator
A1: Split calculator
A2: Enter the amount and method (yellow). Weights: exact ₹, percent, or share units. 'equal' ignores weights.
A4: Amount (₹) | B4: 3000
A5: Method | B5: shares
A7: Member | B7: Weight (input) | C7: Share (₹)
A8: Ananya | B8: 2 | C8: =IF($B$5="equal",IF(COUNTA($A$8:$A$11)>0,$B$4/COUNTA($A$8:$A$11),0),IF($B$5="exact",B8,IF($B$5="percent",$B$4*B8/100,IF(SUM($B$8:$B$11)>0,$B$4*B8/SUM($B$8:$B$11),0))))
A9: Rohan | B9: 1 | C9: =IF($B$5="equal",IF(COUNTA($A$8:$A$11)>0,$B$4/COUNTA($A$8:$A$11),0),IF($B$5="exact",B9,IF($B$5="percent",$B$4*B9/100,IF(SUM($B$8:$B$11)>0,$B$4*B9/SUM($B$8:$B$11),0))))
A10: Diya | B10: 1 | C10: =IF($B$5="equal",IF(COUNTA($A$8:$A$11)>0,$B$4/COUNTA($A$8:$A$11),0),IF($B$5="exact",B10,IF($B$5="percent",$B$4*B10/100,IF(SUM($B$8:$B$11)>0,$B$4*B10/SUM($B$8:$B$11),0))))
A11: Guest | B11: 0 | C11: =IF($B$5="equal",IF(COUNTA($A$8:$A$11)>0,$B$4/COUNTA($A$8:$A$11),0),IF($B$5="exact",B11,IF($B$5="percent",$B$4*B11/100,IF(SUM($B$8:$B$11)>0,$B$4*B11/SUM($B$8:$B$11),0))))
A12: Total of shares | C12: =SUM(C8:C11)
A13: Check | C13: =IF(ROUND(C12-B4,2)=0,"Adds up","Does not add up")
A15: Example: ₹3,000 with shares 2:1:1:0 → ₹1,500 / ₹750 / ₹750 / ₹0. The app rounds to the paisa and gives leftover paise to the largest weights.

Sheet Locations
A1: Country | B1: State / region | C1: City
A2: India | B2: Andhra Pradesh | C2: Visakhapatnam
A3: India | B3: Andhra Pradesh | C3: Vijayawada
A4: India | B4: Andhra Pradesh | C4: Tirupati
A5: India | B5: Andhra Pradesh | C5: Guntur
A6: India | B6: Arunachal Pradesh | C6: Itanagar
A7: India | B7: Arunachal Pradesh | C7: Tawang
A8: India | B8: Assam | C8: Guwahati
A9: India | B9: Assam | C9: Dibrugarh
A10: India | B10: Assam | C10: Silchar
A11: India | B11: Bihar | C11: Patna
A12: India | B12: Bihar | C12: Gaya
... A112: Other… | B112: Other… (type any state or region) | C112: Other… (type any city)
A114: 36 Indian states & union territories, 100 Indian cities, plus 4 other countries. Every level has an 'Other' option for typing a place that isn't listed.

Sheet Catalog
A1: Film | B1: Language | C1: Genre | D1: Certificate | E1: Runtime | F1: Formats
A2: Monsoon Letters | B2: Hindi | C2: Romance · Drama | D2: UA | E2: 2h 18m | F2: 2D / Recliner
A3: Rakshak: The Last Guard | B3: Hindi | C3: Action | D3: UA | E3: 2h 34m | F3: 2D / IMAX / Recliner
A4: Marina Nights | B4: Tamil | C4: Thriller | D4: UA | E4: 2h 26m | F4: 2D / Recliner
A5: Pushpaka Rising | B5: Telugu | C5: Action · Fantasy | D5: UA | E5: 2h 51m | F5: 2D / 3D / IMAX
A6: Kaveri Diaries | B6: Kannada | C6: Drama | D6: U | E6: 2h 05m | F6: 2D
A7: Orbit 9 | B7: English | C7: Sci-fi | D7: UA | E7: 2h 12m | F7: 2D / 3D / IMAX
A8: Ponnonam | B8: Malayalam | C8: Family · Comedy | D8: U | E8: 2h 10m | F8: 2D
A9: Kolkata Noir | B9: Bengali | C9: Mystery | D9: A | E9: 2h 01m | F9: 2D / Recliner
A11: Event types near you
A12: Music | B12: music
A13: Sports | B13: sports
A14: Tech | B14: tech
A15: Comedy | B15: comedy
A16: Theatre | B16: theatre
A17: Food & festivals | B17: food
A19: Films, cinemas, events and venues are fictional demo data, generated for whichever city is selected.

Sheet Flow
A1: Step | B1: Agent / actor | C1: What happens | D1: Output | E1: Where in the app
A2: 1 | B2: Requester | C2: Picks Country → State → City (or 'Other' and types it), then browses Movies / Events / Dining, or types a request such as '3 tickets for Orbit 9 IMAX tomorrow evening'. | D2: Location + request | E2: Top bar · Discover
A3: 2 | B3: Concierge agent | C3: Works out the category, city, date and party size; picks the show and best seats together, the event and ticket tier, or the venue; prices it; proposes who pays; matches a family/friends group. | D3: Priced booking draft | E3: Checkout · Concierge
A4: 3 | B4: Budget agent | C4: Checks the right pot: department quarterly budget, wellbeing allowance or personal monthly budget. | D4: ok / warn / over + notes | E4: Checkout · Budget agent
A5: 4 | B5: Policy agent | C5: Builds the approval chain from ₹ thresholds, per-person caps, compliance categories and budget status; removes self-approval. | D5: Ordered approvers or auto-approval | E5: Checkout · Policy agent
A6: 5 | B6: Requester | C6: Changes who pays / group / purpose if needed and confirms. Movie seats are held immediately. | D6: Booking created | E6: Bookings
A7: 6 | B7: Approval agent | C7: Notifies the current approver; each approves or rejects in order; a rejection stops the chain and releases seats. | D7: Approved / rejected | E7: Approvals
A8: 7 | B8: Booking agent | C8: Confirms with the cinema, organiser or venue and issues m-tickets, e-tickets or a confirmation code. | D8: Confirmed booking | E8: Bookings → details
A9: 8 | B9: Split agent | C9: Shared bookings: posts to the group ledger, computes shares, balances and a fewest-payments settle-up (UPI). | D9: Group ledger entry | E9: Family & friends
A10: 9 | B10: Expense agent | C10: Reimbursable bookings become claimable; the report is drafted with receipts and routed to Finance, HR or Benefits. | D10: Expense report | E10: Expense reports
A11: 10 | B11: Finance / HR / Benefits | C11: Final approval; reimbursement with payroll; the wellbeing allowance is reduced for wellbeing claims. | D11: Reimbursed | E11: Expense reports / Budgets & spend
